cvault/__init__.py
cvault-0.1.2.dist-info/DESCRIPTION.rst
cvault-0.1.2.dist-info/METADATA
cvault-0.1.2.dist-info/RECORD
cvault-0.1.2.dist-info/WHEEL
cvault-0.1.2.dist-info/entry_points.txt
cvault-0.1.2.dist-info/metadata.json
cvault-0.1.2.dist-info/top_level.txt
