Metadata-Version: 2.0
Name: cvault
Version: 0.1.2
Summary: Credential Vault
Home-page: https://github.com/starbops/cvault
Author: Zespre Schmidt
Author-email: starbops@zespre.com
License: MIT
Keywords: credential memo
Platform: any
Classifier: Development Status :: 3 - Alpha
Classifier: Intended Audience :: End Users/Desktop
Classifier: Topic :: Utilities
Classifier: License :: OSI Approved :: MIT License
Classifier: Programming Language :: Python :: 2
Classifier: Programming Language :: Python :: 2.6
Classifier: Programming Language :: Python :: 2.7
Classifier: Programming Language :: Python :: 3
Classifier: Programming Language :: Python :: 3.3
Classifier: Programming Language :: Python :: 3.4
Classifier: Programming Language :: Python :: 3.5
Requires-Dist: docopt
